pybitset-0.0.2.dist-info/RECORD
pybitset-0.0.2.dist-info/METADATA
pybitset-0.0.2.dist-info/WHEEL
pybitset-0.0.2.dist-info/top_level.txt
pybitset/__init__.py
pybitset/backends/__init__.py
pybitset/backends/cffi/__init__.py
pybitset/backends/cffi/_bitset.abi3.so
pybitset/backends/cffi/build.py
pybitset/backends/cython/__init__.py
pybitset/backends/cython/bitset.pxd
pybitset/backends/cython/_bitset.abi3.so
pybitset/backends/cython/_bitset.c
pybitset/backends/cython/_bitset.pyx
